{"butt_1": {"icon": "rte_radio_1.png", "name": "RTE Radio 1", "desc": "Folk, News, Pop"}, "butt_2": {"icon": "newstalk.png", "name": "Newstalk", "desc": "Sport, News, Talk"}, "butt_3": {"icon": "rte_2fm.png", "name": "RT\u00c9 2fm", "desc": "Alternative, Pop, Top 40"}, "butt_4": {"icon": "today_fm.png", "name": "Today FM", "desc": "Adult contemporary"}, "butt_5": {"icon": "spin_1038.png", "name": "Spin 1038", "desc": "Pop, Top 40"}, "butt_6": {"icon": "irelands_classic_hits.png", "name": "Ireland's Classic Hits", "desc": "Classic hits"}, "butt_7": {"icon": "dublins_q102.png", "name": "Dublin's Q102", "desc": "Adult contemporary"}, "butt_8": {"icon": "rte_lyric_fm.png", "name": "RT\u00c9 Lyric FM", "desc": "Classical Music"}, "butt_9": {"icon": "radio_kerry.png", "name": "Radio Kerry", "desc": "Local Service, Adult contemporary"}, "butt_10": {"icon": "rte_gold.png", "name": "RT\u00c9 Gold", "desc": "Classic hits, 50s, 60s"}, "butt_11": {"icon": "98fm.png", "name": "98FM", "desc": "Pop, Adult contemporary"}, "butt_12": {"icon": "cork_s_96fm.png", "name": "Cork's 96FM", "desc": "Local Service, Adult contemporary"}, "butt_13": {"icon": "fm104_live.png", "name": "FM104", "desc": "Top40, Pop"}, "butt_14": {"icon": "radio_nova.png", "name": "Radio Nova", "desc": "Adult contemporary, Adult hits, Rock n Roll"}, "butt_15": {"icon": "midwest_radio.png", "name": "Midwest Radio", "desc": "Local Service"}, "butt_16": {"icon": "corks_redfm.png", "name": "Cork's RedFM", "desc": "Pop, Top 40"}, "butt_17": {"icon": "ocean_fm.png", "name": "Ocean FM", "desc": "Local Service"}, "butt_18": {"icon": "galway_bay_fm.png", "name": "Galway Bay FM", "desc": "Local Service"}, "butt_19": {"icon": "spin_south_west.png", "name": "SPIN South West", "desc": "Top 40, Community"}, "butt_20": {"icon": "live_95.png", "name": "Limerick's Live 95FM", "desc": "Adult contemporary, Local Service"}}